<?xml version="1.0" encoding="UTF-8" standalone="yes"?>
<Properties xmlns="http://schemas.openxmlformats.org/officeDocument/2006/extended-properties" xmlns:vt="http://schemas.openxmlformats.org/officeDocument/2006/docPropsVTypes"><Template>Normal.dotm</Template><TotalTime>11918</TotalTime><Pages>52</Pages><Words>29558</Words><Characters>174393</Characters><Application>Microsoft Office Word</Application><DocSecurity>0</DocSecurity><Lines>2955</Lines><Paragraphs>1009</Paragraphs><ScaleCrop>false</ScaleCrop><Company>Universidad Internacional de La Rioja                                                   Facultad de Educación</Company><LinksUpToDate>false</LinksUpToDate><CharactersWithSpaces>202942</CharactersWithSpaces><SharedDoc>false</SharedDoc><HLinks><vt:vector size="534" baseType="variant"><vt:variant><vt:i4>393291</vt:i4></vt:variant><vt:variant><vt:i4>465</vt:i4></vt:variant><vt:variant><vt:i4>0</vt:i4></vt:variant><vt:variant><vt:i4>5</vt:i4></vt:variant><vt:variant><vt:lpwstr>https://doi.org/10.1080/23311975.2025.2570881</vt:lpwstr></vt:variant><vt:variant><vt:lpwstr></vt:lpwstr></vt:variant><vt:variant><vt:i4>458782</vt:i4></vt:variant><vt:variant><vt:i4>462</vt:i4></vt:variant><vt:variant><vt:i4>0</vt:i4></vt:variant><vt:variant><vt:i4>5</vt:i4></vt:variant><vt:variant><vt:lpwstr>https://arxiv.org/abs/2407.20371</vt:lpwstr></vt:variant><vt:variant><vt:lpwstr></vt:lpwstr></vt:variant><vt:variant><vt:i4>1572944</vt:i4></vt:variant><vt:variant><vt:i4>459</vt:i4></vt:variant><vt:variant><vt:i4>0</vt:i4></vt:variant><vt:variant><vt:i4>5</vt:i4></vt:variant><vt:variant><vt:lpwstr>https://doi.org/10.3390/info14050272</vt:lpwstr></vt:variant><vt:variant><vt:lpwstr></vt:lpwstr></vt:variant><vt:variant><vt:i4>4915204</vt:i4></vt:variant><vt:variant><vt:i4>456</vt:i4></vt:variant><vt:variant><vt:i4>0</vt:i4></vt:variant><vt:variant><vt:i4>5</vt:i4></vt:variant><vt:variant><vt:lpwstr>https://www.mdpi.com/1999-5903/15/11/363</vt:lpwstr></vt:variant><vt:variant><vt:lpwstr></vt:lpwstr></vt:variant><vt:variant><vt:i4>196639</vt:i4></vt:variant><vt:variant><vt:i4>453</vt:i4></vt:variant><vt:variant><vt:i4>0</vt:i4></vt:variant><vt:variant><vt:i4>5</vt:i4></vt:variant><vt:variant><vt:lpwstr>https://arxiv.org/abs/2508.21179</vt:lpwstr></vt:variant><vt:variant><vt:lpwstr></vt:lpwstr></vt:variant><vt:variant><vt:i4>196627</vt:i4></vt:variant><vt:variant><vt:i4>450</vt:i4></vt:variant><vt:variant><vt:i4>0</vt:i4></vt:variant><vt:variant><vt:i4>5</vt:i4></vt:variant><vt:variant><vt:lpwstr>https://arxiv.org/abs/2406.18125</vt:lpwstr></vt:variant><vt:variant><vt:lpwstr></vt:lpwstr></vt:variant><vt:variant><vt:i4>6291567</vt:i4></vt:variant><vt:variant><vt:i4>447</vt:i4></vt:variant><vt:variant><vt:i4>0</vt:i4></vt:variant><vt:variant><vt:i4>5</vt:i4></vt:variant><vt:variant><vt:lpwstr>https://doi.org/10.3390/electronics14040794</vt:lpwstr></vt:variant><vt:variant><vt:lpwstr></vt:lpwstr></vt:variant><vt:variant><vt:i4>720921</vt:i4></vt:variant><vt:variant><vt:i4>444</vt:i4></vt:variant><vt:variant><vt:i4>0</vt:i4></vt:variant><vt:variant><vt:i4>5</vt:i4></vt:variant><vt:variant><vt:lpwstr>https://arxiv.org/abs/2405.19699</vt:lpwstr></vt:variant><vt:variant><vt:lpwstr></vt:lpwstr></vt:variant><vt:variant><vt:i4>3211361</vt:i4></vt:variant><vt:variant><vt:i4>441</vt:i4></vt:variant><vt:variant><vt:i4>0</vt:i4></vt:variant><vt:variant><vt:i4>5</vt:i4></vt:variant><vt:variant><vt:lpwstr>https://doi.org/10.1145/3351095.3372828</vt:lpwstr></vt:variant><vt:variant><vt:lpwstr></vt:lpwstr></vt:variant><vt:variant><vt:i4>2424874</vt:i4></vt:variant><vt:variant><vt:i4>438</vt:i4></vt:variant><vt:variant><vt:i4>0</vt:i4></vt:variant><vt:variant><vt:i4>5</vt:i4></vt:variant><vt:variant><vt:lpwstr>https://admindatahandbook.mit.edu/</vt:lpwstr></vt:variant><vt:variant><vt:lpwstr></vt:lpwstr></vt:variant><vt:variant><vt:i4>65548</vt:i4></vt:variant><vt:variant><vt:i4>435</vt:i4></vt:variant><vt:variant><vt:i4>0</vt:i4></vt:variant><vt:variant><vt:i4>5</vt:i4></vt:variant><vt:variant><vt:lpwstr>https://doi.org/10.1093/pnasnexus/pgaf089</vt:lpwstr></vt:variant><vt:variant><vt:lpwstr></vt:lpwstr></vt:variant><vt:variant><vt:i4>851996</vt:i4></vt:variant><vt:variant><vt:i4>432</vt:i4></vt:variant><vt:variant><vt:i4>0</vt:i4></vt:variant><vt:variant><vt:i4>5</vt:i4></vt:variant><vt:variant><vt:lpwstr>https://arxiv.org/abs/2504.02870</vt:lpwstr></vt:variant><vt:variant><vt:lpwstr></vt:lpwstr></vt:variant><vt:variant><vt:i4>3735662</vt:i4></vt:variant><vt:variant><vt:i4>429</vt:i4></vt:variant><vt:variant><vt:i4>0</vt:i4></vt:variant><vt:variant><vt:i4>5</vt:i4></vt:variant><vt:variant><vt:lpwstr>https://doi.org/10.1145/3778450.3778452</vt:lpwstr></vt:variant><vt:variant><vt:lpwstr></vt:lpwstr></vt:variant><vt:variant><vt:i4>524319</vt:i4></vt:variant><vt:variant><vt:i4>426</vt:i4></vt:variant><vt:variant><vt:i4>0</vt:i4></vt:variant><vt:variant><vt:i4>5</vt:i4></vt:variant><vt:variant><vt:lpwstr>https://arxiv.org/abs/2109.06501</vt:lpwstr></vt:variant><vt:variant><vt:lpwstr></vt:lpwstr></vt:variant><vt:variant><vt:i4>1179742</vt:i4></vt:variant><vt:variant><vt:i4>423</vt:i4></vt:variant><vt:variant><vt:i4>0</vt:i4></vt:variant><vt:variant><vt:i4>5</vt:i4></vt:variant><vt:variant><vt:lpwstr>https://doi.org/10.1177/23794607251353585</vt:lpwstr></vt:variant><vt:variant><vt:lpwstr></vt:lpwstr></vt:variant><vt:variant><vt:i4>1966094</vt:i4></vt:variant><vt:variant><vt:i4>420</vt:i4></vt:variant><vt:variant><vt:i4>0</vt:i4></vt:variant><vt:variant><vt:i4>5</vt:i4></vt:variant><vt:variant><vt:lpwstr>https://doi.org/10.17979/ja-cea.2025.46.12139</vt:lpwstr></vt:variant><vt:variant><vt:lpwstr></vt:lpwstr></vt:variant><vt:variant><vt:i4>3276902</vt:i4></vt:variant><vt:variant><vt:i4>417</vt:i4></vt:variant><vt:variant><vt:i4>0</vt:i4></vt:variant><vt:variant><vt:i4>5</vt:i4></vt:variant><vt:variant><vt:lpwstr>https://doi.org/10.1145/3630106.3658933</vt:lpwstr></vt:variant><vt:variant><vt:lpwstr></vt:lpwstr></vt:variant><vt:variant><vt:i4>8323193</vt:i4></vt:variant><vt:variant><vt:i4>414</vt:i4></vt:variant><vt:variant><vt:i4>0</vt:i4></vt:variant><vt:variant><vt:i4>5</vt:i4></vt:variant><vt:variant><vt:lpwstr>https://doi.org/10.2197/ipsjjip.32.881</vt:lpwstr></vt:variant><vt:variant><vt:lpwstr></vt:lpwstr></vt:variant><vt:variant><vt:i4>327700</vt:i4></vt:variant><vt:variant><vt:i4>411</vt:i4></vt:variant><vt:variant><vt:i4>0</vt:i4></vt:variant><vt:variant><vt:i4>5</vt:i4></vt:variant><vt:variant><vt:lpwstr>https://arxiv.org/abs/2510.05490</vt:lpwstr></vt:variant><vt:variant><vt:lpwstr></vt:lpwstr></vt:variant><vt:variant><vt:i4>2228320</vt:i4></vt:variant><vt:variant><vt:i4>408</vt:i4></vt:variant><vt:variant><vt:i4>0</vt:i4></vt:variant><vt:variant><vt:i4>5</vt:i4></vt:variant><vt:variant><vt:lpwstr>https://doi.org/10.1145/3696457</vt:lpwstr></vt:variant><vt:variant><vt:lpwstr></vt:lpwstr></vt:variant><vt:variant><vt:i4>327757</vt:i4></vt:variant><vt:variant><vt:i4>405</vt:i4></vt:variant><vt:variant><vt:i4>0</vt:i4></vt:variant><vt:variant><vt:i4>5</vt:i4></vt:variant><vt:variant><vt:lpwstr>https://doi.org/10.2139/ssrn.5314976</vt:lpwstr></vt:variant><vt:variant><vt:lpwstr></vt:lpwstr></vt:variant><vt:variant><vt:i4>6160459</vt:i4></vt:variant><vt:variant><vt:i4>402</vt:i4></vt:variant><vt:variant><vt:i4>0</vt:i4></vt:variant><vt:variant><vt:i4>5</vt:i4></vt:variant><vt:variant><vt:lpwstr>https://doi.org/10.1089/big.2016.0047</vt:lpwstr></vt:variant><vt:variant><vt:lpwstr></vt:lpwstr></vt:variant><vt:variant><vt:i4>917590</vt:i4></vt:variant><vt:variant><vt:i4>399</vt:i4></vt:variant><vt:variant><vt:i4>0</vt:i4></vt:variant><vt:variant><vt:i4>5</vt:i4></vt:variant><vt:variant><vt:lpwstr>https://aclanthology.org/2022.legal-1.11</vt:lpwstr></vt:variant><vt:variant><vt:lpwstr></vt:lpwstr></vt:variant><vt:variant><vt:i4>6488126</vt:i4></vt:variant><vt:variant><vt:i4>396</vt:i4></vt:variant><vt:variant><vt:i4>0</vt:i4></vt:variant><vt:variant><vt:i4>5</vt:i4></vt:variant><vt:variant><vt:lpwstr>https://doi.org/10.1007/s43681-025-00844-z</vt:lpwstr></vt:variant><vt:variant><vt:lpwstr></vt:lpwstr></vt:variant><vt:variant><vt:i4>7274532</vt:i4></vt:variant><vt:variant><vt:i4>393</vt:i4></vt:variant><vt:variant><vt:i4>0</vt:i4></vt:variant><vt:variant><vt:i4>5</vt:i4></vt:variant><vt:variant><vt:lpwstr>https://ranlp.org/</vt:lpwstr></vt:variant><vt:variant><vt:lpwstr></vt:lpwstr></vt:variant><vt:variant><vt:i4>2555921</vt:i4></vt:variant><vt:variant><vt:i4>390</vt:i4></vt:variant><vt:variant><vt:i4>0</vt:i4></vt:variant><vt:variant><vt:i4>5</vt:i4></vt:variant><vt:variant><vt:lpwstr>https://www.theseus.fi/bitstream/handle/10024/905692/Abidizadegan_Fatemeh.pdf</vt:lpwstr></vt:variant><vt:variant><vt:lpwstr></vt:lpwstr></vt:variant><vt:variant><vt:i4>1114165</vt:i4></vt:variant><vt:variant><vt:i4>380</vt:i4></vt:variant><vt:variant><vt:i4>0</vt:i4></vt:variant><vt:variant><vt:i4>5</vt:i4></vt:variant><vt:variant><vt:lpwstr></vt:lpwstr></vt:variant><vt:variant><vt:lpwstr>_Toc158282432</vt:lpwstr></vt:variant><vt:variant><vt:i4>1769527</vt:i4></vt:variant><vt:variant><vt:i4>371</vt:i4></vt:variant><vt:variant><vt:i4>0</vt:i4></vt:variant><vt:variant><vt:i4>5</vt:i4></vt:variant><vt:variant><vt:lpwstr></vt:lpwstr></vt:variant><vt:variant><vt:lpwstr>_Toc155946760</vt:lpwstr></vt:variant><vt:variant><vt:i4>1572919</vt:i4></vt:variant><vt:variant><vt:i4>362</vt:i4></vt:variant><vt:variant><vt:i4>0</vt:i4></vt:variant><vt:variant><vt:i4>5</vt:i4></vt:variant><vt:variant><vt:lpwstr></vt:lpwstr></vt:variant><vt:variant><vt:lpwstr>_Toc225925219</vt:lpwstr></vt:variant><vt:variant><vt:i4>1572919</vt:i4></vt:variant><vt:variant><vt:i4>356</vt:i4></vt:variant><vt:variant><vt:i4>0</vt:i4></vt:variant><vt:variant><vt:i4>5</vt:i4></vt:variant><vt:variant><vt:lpwstr></vt:lpwstr></vt:variant><vt:variant><vt:lpwstr>_Toc225925218</vt:lpwstr></vt:variant><vt:variant><vt:i4>1572919</vt:i4></vt:variant><vt:variant><vt:i4>350</vt:i4></vt:variant><vt:variant><vt:i4>0</vt:i4></vt:variant><vt:variant><vt:i4>5</vt:i4></vt:variant><vt:variant><vt:lpwstr></vt:lpwstr></vt:variant><vt:variant><vt:lpwstr>_Toc225925217</vt:lpwstr></vt:variant><vt:variant><vt:i4>1572919</vt:i4></vt:variant><vt:variant><vt:i4>344</vt:i4></vt:variant><vt:variant><vt:i4>0</vt:i4></vt:variant><vt:variant><vt:i4>5</vt:i4></vt:variant><vt:variant><vt:lpwstr></vt:lpwstr></vt:variant><vt:variant><vt:lpwstr>_Toc225925216</vt:lpwstr></vt:variant><vt:variant><vt:i4>1572919</vt:i4></vt:variant><vt:variant><vt:i4>338</vt:i4></vt:variant><vt:variant><vt:i4>0</vt:i4></vt:variant><vt:variant><vt:i4>5</vt:i4></vt:variant><vt:variant><vt:lpwstr></vt:lpwstr></vt:variant><vt:variant><vt:lpwstr>_Toc225925215</vt:lpwstr></vt:variant><vt:variant><vt:i4>1572919</vt:i4></vt:variant><vt:variant><vt:i4>332</vt:i4></vt:variant><vt:variant><vt:i4>0</vt:i4></vt:variant><vt:variant><vt:i4>5</vt:i4></vt:variant><vt:variant><vt:lpwstr></vt:lpwstr></vt:variant><vt:variant><vt:lpwstr>_Toc225925214</vt:lpwstr></vt:variant><vt:variant><vt:i4>1572919</vt:i4></vt:variant><vt:variant><vt:i4>326</vt:i4></vt:variant><vt:variant><vt:i4>0</vt:i4></vt:variant><vt:variant><vt:i4>5</vt:i4></vt:variant><vt:variant><vt:lpwstr></vt:lpwstr></vt:variant><vt:variant><vt:lpwstr>_Toc225925213</vt:lpwstr></vt:variant><vt:variant><vt:i4>1572919</vt:i4></vt:variant><vt:variant><vt:i4>320</vt:i4></vt:variant><vt:variant><vt:i4>0</vt:i4></vt:variant><vt:variant><vt:i4>5</vt:i4></vt:variant><vt:variant><vt:lpwstr></vt:lpwstr></vt:variant><vt:variant><vt:lpwstr>_Toc225925212</vt:lpwstr></vt:variant><vt:variant><vt:i4>1572919</vt:i4></vt:variant><vt:variant><vt:i4>314</vt:i4></vt:variant><vt:variant><vt:i4>0</vt:i4></vt:variant><vt:variant><vt:i4>5</vt:i4></vt:variant><vt:variant><vt:lpwstr></vt:lpwstr></vt:variant><vt:variant><vt:lpwstr>_Toc225925211</vt:lpwstr></vt:variant><vt:variant><vt:i4>1572919</vt:i4></vt:variant><vt:variant><vt:i4>308</vt:i4></vt:variant><vt:variant><vt:i4>0</vt:i4></vt:variant><vt:variant><vt:i4>5</vt:i4></vt:variant><vt:variant><vt:lpwstr></vt:lpwstr></vt:variant><vt:variant><vt:lpwstr>_Toc225925210</vt:lpwstr></vt:variant><vt:variant><vt:i4>1638455</vt:i4></vt:variant><vt:variant><vt:i4>302</vt:i4></vt:variant><vt:variant><vt:i4>0</vt:i4></vt:variant><vt:variant><vt:i4>5</vt:i4></vt:variant><vt:variant><vt:lpwstr></vt:lpwstr></vt:variant><vt:variant><vt:lpwstr>_Toc225925209</vt:lpwstr></vt:variant><vt:variant><vt:i4>1638455</vt:i4></vt:variant><vt:variant><vt:i4>296</vt:i4></vt:variant><vt:variant><vt:i4>0</vt:i4></vt:variant><vt:variant><vt:i4>5</vt:i4></vt:variant><vt:variant><vt:lpwstr></vt:lpwstr></vt:variant><vt:variant><vt:lpwstr>_Toc225925208</vt:lpwstr></vt:variant><vt:variant><vt:i4>1638455</vt:i4></vt:variant><vt:variant><vt:i4>290</vt:i4></vt:variant><vt:variant><vt:i4>0</vt:i4></vt:variant><vt:variant><vt:i4>5</vt:i4></vt:variant><vt:variant><vt:lpwstr></vt:lpwstr></vt:variant><vt:variant><vt:lpwstr>_Toc225925207</vt:lpwstr></vt:variant><vt:variant><vt:i4>1638455</vt:i4></vt:variant><vt:variant><vt:i4>284</vt:i4></vt:variant><vt:variant><vt:i4>0</vt:i4></vt:variant><vt:variant><vt:i4>5</vt:i4></vt:variant><vt:variant><vt:lpwstr></vt:lpwstr></vt:variant><vt:variant><vt:lpwstr>_Toc225925206</vt:lpwstr></vt:variant><vt:variant><vt:i4>1638455</vt:i4></vt:variant><vt:variant><vt:i4>278</vt:i4></vt:variant><vt:variant><vt:i4>0</vt:i4></vt:variant><vt:variant><vt:i4>5</vt:i4></vt:variant><vt:variant><vt:lpwstr></vt:lpwstr></vt:variant><vt:variant><vt:lpwstr>_Toc225925205</vt:lpwstr></vt:variant><vt:variant><vt:i4>1638455</vt:i4></vt:variant><vt:variant><vt:i4>272</vt:i4></vt:variant><vt:variant><vt:i4>0</vt:i4></vt:variant><vt:variant><vt:i4>5</vt:i4></vt:variant><vt:variant><vt:lpwstr></vt:lpwstr></vt:variant><vt:variant><vt:lpwstr>_Toc225925204</vt:lpwstr></vt:variant><vt:variant><vt:i4>1638455</vt:i4></vt:variant><vt:variant><vt:i4>266</vt:i4></vt:variant><vt:variant><vt:i4>0</vt:i4></vt:variant><vt:variant><vt:i4>5</vt:i4></vt:variant><vt:variant><vt:lpwstr></vt:lpwstr></vt:variant><vt:variant><vt:lpwstr>_Toc225925203</vt:lpwstr></vt:variant><vt:variant><vt:i4>1638455</vt:i4></vt:variant><vt:variant><vt:i4>260</vt:i4></vt:variant><vt:variant><vt:i4>0</vt:i4></vt:variant><vt:variant><vt:i4>5</vt:i4></vt:variant><vt:variant><vt:lpwstr></vt:lpwstr></vt:variant><vt:variant><vt:lpwstr>_Toc225925202</vt:lpwstr></vt:variant><vt:variant><vt:i4>1638455</vt:i4></vt:variant><vt:variant><vt:i4>254</vt:i4></vt:variant><vt:variant><vt:i4>0</vt:i4></vt:variant><vt:variant><vt:i4>5</vt:i4></vt:variant><vt:variant><vt:lpwstr></vt:lpwstr></vt:variant><vt:variant><vt:lpwstr>_Toc225925201</vt:lpwstr></vt:variant><vt:variant><vt:i4>1638455</vt:i4></vt:variant><vt:variant><vt:i4>248</vt:i4></vt:variant><vt:variant><vt:i4>0</vt:i4></vt:variant><vt:variant><vt:i4>5</vt:i4></vt:variant><vt:variant><vt:lpwstr></vt:lpwstr></vt:variant><vt:variant><vt:lpwstr>_Toc225925200</vt:lpwstr></vt:variant><vt:variant><vt:i4>1048628</vt:i4></vt:variant><vt:variant><vt:i4>242</vt:i4></vt:variant><vt:variant><vt:i4>0</vt:i4></vt:variant><vt:variant><vt:i4>5</vt:i4></vt:variant><vt:variant><vt:lpwstr></vt:lpwstr></vt:variant><vt:variant><vt:lpwstr>_Toc225925199</vt:lpwstr></vt:variant><vt:variant><vt:i4>1048628</vt:i4></vt:variant><vt:variant><vt:i4>236</vt:i4></vt:variant><vt:variant><vt:i4>0</vt:i4></vt:variant><vt:variant><vt:i4>5</vt:i4></vt:variant><vt:variant><vt:lpwstr></vt:lpwstr></vt:variant><vt:variant><vt:lpwstr>_Toc225925198</vt:lpwstr></vt:variant><vt:variant><vt:i4>1048628</vt:i4></vt:variant><vt:variant><vt:i4>230</vt:i4></vt:variant><vt:variant><vt:i4>0</vt:i4></vt:variant><vt:variant><vt:i4>5</vt:i4></vt:variant><vt:variant><vt:lpwstr></vt:lpwstr></vt:variant><vt:variant><vt:lpwstr>_Toc225925197</vt:lpwstr></vt:variant><vt:variant><vt:i4>1048628</vt:i4></vt:variant><vt:variant><vt:i4>224</vt:i4></vt:variant><vt:variant><vt:i4>0</vt:i4></vt:variant><vt:variant><vt:i4>5</vt:i4></vt:variant><vt:variant><vt:lpwstr></vt:lpwstr></vt:variant><vt:variant><vt:lpwstr>_Toc225925196</vt:lpwstr></vt:variant><vt:variant><vt:i4>1048628</vt:i4></vt:variant><vt:variant><vt:i4>218</vt:i4></vt:variant><vt:variant><vt:i4>0</vt:i4></vt:variant><vt:variant><vt:i4>5</vt:i4></vt:variant><vt:variant><vt:lpwstr></vt:lpwstr></vt:variant><vt:variant><vt:lpwstr>_Toc225925195</vt:lpwstr></vt:variant><vt:variant><vt:i4>1048628</vt:i4></vt:variant><vt:variant><vt:i4>212</vt:i4></vt:variant><vt:variant><vt:i4>0</vt:i4></vt:variant><vt:variant><vt:i4>5</vt:i4></vt:variant><vt:variant><vt:lpwstr></vt:lpwstr></vt:variant><vt:variant><vt:lpwstr>_Toc225925194</vt:lpwstr></vt:variant><vt:variant><vt:i4>1048628</vt:i4></vt:variant><vt:variant><vt:i4>206</vt:i4></vt:variant><vt:variant><vt:i4>0</vt:i4></vt:variant><vt:variant><vt:i4>5</vt:i4></vt:variant><vt:variant><vt:lpwstr></vt:lpwstr></vt:variant><vt:variant><vt:lpwstr>_Toc225925193</vt:lpwstr></vt:variant><vt:variant><vt:i4>1048628</vt:i4></vt:variant><vt:variant><vt:i4>200</vt:i4></vt:variant><vt:variant><vt:i4>0</vt:i4></vt:variant><vt:variant><vt:i4>5</vt:i4></vt:variant><vt:variant><vt:lpwstr></vt:lpwstr></vt:variant><vt:variant><vt:lpwstr>_Toc225925192</vt:lpwstr></vt:variant><vt:variant><vt:i4>1048628</vt:i4></vt:variant><vt:variant><vt:i4>194</vt:i4></vt:variant><vt:variant><vt:i4>0</vt:i4></vt:variant><vt:variant><vt:i4>5</vt:i4></vt:variant><vt:variant><vt:lpwstr></vt:lpwstr></vt:variant><vt:variant><vt:lpwstr>_Toc225925191</vt:lpwstr></vt:variant><vt:variant><vt:i4>1048628</vt:i4></vt:variant><vt:variant><vt:i4>188</vt:i4></vt:variant><vt:variant><vt:i4>0</vt:i4></vt:variant><vt:variant><vt:i4>5</vt:i4></vt:variant><vt:variant><vt:lpwstr></vt:lpwstr></vt:variant><vt:variant><vt:lpwstr>_Toc225925190</vt:lpwstr></vt:variant><vt:variant><vt:i4>1114164</vt:i4></vt:variant><vt:variant><vt:i4>182</vt:i4></vt:variant><vt:variant><vt:i4>0</vt:i4></vt:variant><vt:variant><vt:i4>5</vt:i4></vt:variant><vt:variant><vt:lpwstr></vt:lpwstr></vt:variant><vt:variant><vt:lpwstr>_Toc225925189</vt:lpwstr></vt:variant><vt:variant><vt:i4>1114164</vt:i4></vt:variant><vt:variant><vt:i4>176</vt:i4></vt:variant><vt:variant><vt:i4>0</vt:i4></vt:variant><vt:variant><vt:i4>5</vt:i4></vt:variant><vt:variant><vt:lpwstr></vt:lpwstr></vt:variant><vt:variant><vt:lpwstr>_Toc225925188</vt:lpwstr></vt:variant><vt:variant><vt:i4>1114164</vt:i4></vt:variant><vt:variant><vt:i4>170</vt:i4></vt:variant><vt:variant><vt:i4>0</vt:i4></vt:variant><vt:variant><vt:i4>5</vt:i4></vt:variant><vt:variant><vt:lpwstr></vt:lpwstr></vt:variant><vt:variant><vt:lpwstr>_Toc225925187</vt:lpwstr></vt:variant><vt:variant><vt:i4>1114164</vt:i4></vt:variant><vt:variant><vt:i4>164</vt:i4></vt:variant><vt:variant><vt:i4>0</vt:i4></vt:variant><vt:variant><vt:i4>5</vt:i4></vt:variant><vt:variant><vt:lpwstr></vt:lpwstr></vt:variant><vt:variant><vt:lpwstr>_Toc225925186</vt:lpwstr></vt:variant><vt:variant><vt:i4>1114164</vt:i4></vt:variant><vt:variant><vt:i4>158</vt:i4></vt:variant><vt:variant><vt:i4>0</vt:i4></vt:variant><vt:variant><vt:i4>5</vt:i4></vt:variant><vt:variant><vt:lpwstr></vt:lpwstr></vt:variant><vt:variant><vt:lpwstr>_Toc225925185</vt:lpwstr></vt:variant><vt:variant><vt:i4>1114164</vt:i4></vt:variant><vt:variant><vt:i4>152</vt:i4></vt:variant><vt:variant><vt:i4>0</vt:i4></vt:variant><vt:variant><vt:i4>5</vt:i4></vt:variant><vt:variant><vt:lpwstr></vt:lpwstr></vt:variant><vt:variant><vt:lpwstr>_Toc225925184</vt:lpwstr></vt:variant><vt:variant><vt:i4>1114164</vt:i4></vt:variant><vt:variant><vt:i4>146</vt:i4></vt:variant><vt:variant><vt:i4>0</vt:i4></vt:variant><vt:variant><vt:i4>5</vt:i4></vt:variant><vt:variant><vt:lpwstr></vt:lpwstr></vt:variant><vt:variant><vt:lpwstr>_Toc225925183</vt:lpwstr></vt:variant><vt:variant><vt:i4>1114164</vt:i4></vt:variant><vt:variant><vt:i4>140</vt:i4></vt:variant><vt:variant><vt:i4>0</vt:i4></vt:variant><vt:variant><vt:i4>5</vt:i4></vt:variant><vt:variant><vt:lpwstr></vt:lpwstr></vt:variant><vt:variant><vt:lpwstr>_Toc225925182</vt:lpwstr></vt:variant><vt:variant><vt:i4>1114164</vt:i4></vt:variant><vt:variant><vt:i4>134</vt:i4></vt:variant><vt:variant><vt:i4>0</vt:i4></vt:variant><vt:variant><vt:i4>5</vt:i4></vt:variant><vt:variant><vt:lpwstr></vt:lpwstr></vt:variant><vt:variant><vt:lpwstr>_Toc225925181</vt:lpwstr></vt:variant><vt:variant><vt:i4>1114164</vt:i4></vt:variant><vt:variant><vt:i4>128</vt:i4></vt:variant><vt:variant><vt:i4>0</vt:i4></vt:variant><vt:variant><vt:i4>5</vt:i4></vt:variant><vt:variant><vt:lpwstr></vt:lpwstr></vt:variant><vt:variant><vt:lpwstr>_Toc225925180</vt:lpwstr></vt:variant><vt:variant><vt:i4>1966132</vt:i4></vt:variant><vt:variant><vt:i4>122</vt:i4></vt:variant><vt:variant><vt:i4>0</vt:i4></vt:variant><vt:variant><vt:i4>5</vt:i4></vt:variant><vt:variant><vt:lpwstr></vt:lpwstr></vt:variant><vt:variant><vt:lpwstr>_Toc225925179</vt:lpwstr></vt:variant><vt:variant><vt:i4>1966132</vt:i4></vt:variant><vt:variant><vt:i4>116</vt:i4></vt:variant><vt:variant><vt:i4>0</vt:i4></vt:variant><vt:variant><vt:i4>5</vt:i4></vt:variant><vt:variant><vt:lpwstr></vt:lpwstr></vt:variant><vt:variant><vt:lpwstr>_Toc225925178</vt:lpwstr></vt:variant><vt:variant><vt:i4>1966132</vt:i4></vt:variant><vt:variant><vt:i4>110</vt:i4></vt:variant><vt:variant><vt:i4>0</vt:i4></vt:variant><vt:variant><vt:i4>5</vt:i4></vt:variant><vt:variant><vt:lpwstr></vt:lpwstr></vt:variant><vt:variant><vt:lpwstr>_Toc225925177</vt:lpwstr></vt:variant><vt:variant><vt:i4>1966132</vt:i4></vt:variant><vt:variant><vt:i4>104</vt:i4></vt:variant><vt:variant><vt:i4>0</vt:i4></vt:variant><vt:variant><vt:i4>5</vt:i4></vt:variant><vt:variant><vt:lpwstr></vt:lpwstr></vt:variant><vt:variant><vt:lpwstr>_Toc225925176</vt:lpwstr></vt:variant><vt:variant><vt:i4>1966132</vt:i4></vt:variant><vt:variant><vt:i4>98</vt:i4></vt:variant><vt:variant><vt:i4>0</vt:i4></vt:variant><vt:variant><vt:i4>5</vt:i4></vt:variant><vt:variant><vt:lpwstr></vt:lpwstr></vt:variant><vt:variant><vt:lpwstr>_Toc225925175</vt:lpwstr></vt:variant><vt:variant><vt:i4>1966132</vt:i4></vt:variant><vt:variant><vt:i4>92</vt:i4></vt:variant><vt:variant><vt:i4>0</vt:i4></vt:variant><vt:variant><vt:i4>5</vt:i4></vt:variant><vt:variant><vt:lpwstr></vt:lpwstr></vt:variant><vt:variant><vt:lpwstr>_Toc225925174</vt:lpwstr></vt:variant><vt:variant><vt:i4>1966132</vt:i4></vt:variant><vt:variant><vt:i4>86</vt:i4></vt:variant><vt:variant><vt:i4>0</vt:i4></vt:variant><vt:variant><vt:i4>5</vt:i4></vt:variant><vt:variant><vt:lpwstr></vt:lpwstr></vt:variant><vt:variant><vt:lpwstr>_Toc225925173</vt:lpwstr></vt:variant><vt:variant><vt:i4>1966132</vt:i4></vt:variant><vt:variant><vt:i4>80</vt:i4></vt:variant><vt:variant><vt:i4>0</vt:i4></vt:variant><vt:variant><vt:i4>5</vt:i4></vt:variant><vt:variant><vt:lpwstr></vt:lpwstr></vt:variant><vt:variant><vt:lpwstr>_Toc225925172</vt:lpwstr></vt:variant><vt:variant><vt:i4>1966132</vt:i4></vt:variant><vt:variant><vt:i4>74</vt:i4></vt:variant><vt:variant><vt:i4>0</vt:i4></vt:variant><vt:variant><vt:i4>5</vt:i4></vt:variant><vt:variant><vt:lpwstr></vt:lpwstr></vt:variant><vt:variant><vt:lpwstr>_Toc225925171</vt:lpwstr></vt:variant><vt:variant><vt:i4>1966132</vt:i4></vt:variant><vt:variant><vt:i4>68</vt:i4></vt:variant><vt:variant><vt:i4>0</vt:i4></vt:variant><vt:variant><vt:i4>5</vt:i4></vt:variant><vt:variant><vt:lpwstr></vt:lpwstr></vt:variant><vt:variant><vt:lpwstr>_Toc225925170</vt:lpwstr></vt:variant><vt:variant><vt:i4>2031668</vt:i4></vt:variant><vt:variant><vt:i4>62</vt:i4></vt:variant><vt:variant><vt:i4>0</vt:i4></vt:variant><vt:variant><vt:i4>5</vt:i4></vt:variant><vt:variant><vt:lpwstr></vt:lpwstr></vt:variant><vt:variant><vt:lpwstr>_Toc225925169</vt:lpwstr></vt:variant><vt:variant><vt:i4>2031668</vt:i4></vt:variant><vt:variant><vt:i4>56</vt:i4></vt:variant><vt:variant><vt:i4>0</vt:i4></vt:variant><vt:variant><vt:i4>5</vt:i4></vt:variant><vt:variant><vt:lpwstr></vt:lpwstr></vt:variant><vt:variant><vt:lpwstr>_Toc225925168</vt:lpwstr></vt:variant><vt:variant><vt:i4>2031668</vt:i4></vt:variant><vt:variant><vt:i4>50</vt:i4></vt:variant><vt:variant><vt:i4>0</vt:i4></vt:variant><vt:variant><vt:i4>5</vt:i4></vt:variant><vt:variant><vt:lpwstr></vt:lpwstr></vt:variant><vt:variant><vt:lpwstr>_Toc225925167</vt:lpwstr></vt:variant><vt:variant><vt:i4>2031668</vt:i4></vt:variant><vt:variant><vt:i4>44</vt:i4></vt:variant><vt:variant><vt:i4>0</vt:i4></vt:variant><vt:variant><vt:i4>5</vt:i4></vt:variant><vt:variant><vt:lpwstr></vt:lpwstr></vt:variant><vt:variant><vt:lpwstr>_Toc225925166</vt:lpwstr></vt:variant><vt:variant><vt:i4>2031668</vt:i4></vt:variant><vt:variant><vt:i4>38</vt:i4></vt:variant><vt:variant><vt:i4>0</vt:i4></vt:variant><vt:variant><vt:i4>5</vt:i4></vt:variant><vt:variant><vt:lpwstr></vt:lpwstr></vt:variant><vt:variant><vt:lpwstr>_Toc225925165</vt:lpwstr></vt:variant><vt:variant><vt:i4>2031668</vt:i4></vt:variant><vt:variant><vt:i4>32</vt:i4></vt:variant><vt:variant><vt:i4>0</vt:i4></vt:variant><vt:variant><vt:i4>5</vt:i4></vt:variant><vt:variant><vt:lpwstr></vt:lpwstr></vt:variant><vt:variant><vt:lpwstr>_Toc225925164</vt:lpwstr></vt:variant><vt:variant><vt:i4>2031668</vt:i4></vt:variant><vt:variant><vt:i4>26</vt:i4></vt:variant><vt:variant><vt:i4>0</vt:i4></vt:variant><vt:variant><vt:i4>5</vt:i4></vt:variant><vt:variant><vt:lpwstr></vt:lpwstr></vt:variant><vt:variant><vt:lpwstr>_Toc225925163</vt:lpwstr></vt:variant><vt:variant><vt:i4>2031668</vt:i4></vt:variant><vt:variant><vt:i4>20</vt:i4></vt:variant><vt:variant><vt:i4>0</vt:i4></vt:variant><vt:variant><vt:i4>5</vt:i4></vt:variant><vt:variant><vt:lpwstr></vt:lpwstr></vt:variant><vt:variant><vt:lpwstr>_Toc225925162</vt:lpwstr></vt:variant><vt:variant><vt:i4>2031668</vt:i4></vt:variant><vt:variant><vt:i4>14</vt:i4></vt:variant><vt:variant><vt:i4>0</vt:i4></vt:variant><vt:variant><vt:i4>5</vt:i4></vt:variant><vt:variant><vt:lpwstr></vt:lpwstr></vt:variant><vt:variant><vt:lpwstr>_Toc225925161</vt:lpwstr></vt:variant><vt:variant><vt:i4>2031668</vt:i4></vt:variant><vt:variant><vt:i4>8</vt:i4></vt:variant><vt:variant><vt:i4>0</vt:i4></vt:variant><vt:variant><vt:i4>5</vt:i4></vt:variant><vt:variant><vt:lpwstr></vt:lpwstr></vt:variant><vt:variant><vt:lpwstr>_Toc225925160</vt:lpwstr></vt:variant><vt:variant><vt:i4>1835060</vt:i4></vt:variant><vt:variant><vt:i4>2</vt:i4></vt:variant><vt:variant><vt:i4>0</vt:i4></vt:variant><vt:variant><vt:i4>5</vt:i4></vt:variant><vt:variant><vt:lpwstr></vt:lpwstr></vt:variant><vt:variant><vt:lpwstr>_Toc225925159</vt:lpwstr></vt:variant></vt:vector></HLinks><HyperlinksChanged>false</HyperlinksChanged><AppVersion>16.0000</AppVersion></Properties>